MANIFEST.in
README.txt
setup.cfg
setup.py
docs/HISTORY.txt
docs/INSTALL.txt
docs/LICENSE.GPL
docs/LICENSE.txt
iservices/__init__.py
iservices/__init__.pyc
iservices.rssdocument.egg-info/PKG-INFO
iservices.rssdocument.egg-info/SOURCES.txt
iservices.rssdocument.egg-info/dependency_links.txt
iservices.rssdocument.egg-info/entry_points.txt
iservices.rssdocument.egg-info/namespace_packages.txt
iservices.rssdocument.egg-info/not-zip-safe
iservices.rssdocument.egg-info/paster_plugins.txt
iservices.rssdocument.egg-info/requires.txt
iservices.rssdocument.egg-info/top_level.txt
iservices/rssdocument/__init__.py
iservices/rssdocument/__init__.pyc
iservices/rssdocument/config.py
iservices/rssdocument/config.pyc
iservices/rssdocument/configure.zcml
iservices/rssdocument/interfaces.py
iservices/rssdocument/interfaces.pyc
iservices/rssdocument/version.txt
iservices/rssdocument/browser/__init__.py
iservices/rssdocument/browser/__init__.pyc
iservices/rssdocument/browser/configure.zcml
iservices/rssdocument/browser/rsscode.py
iservices/rssdocument/browser/rsscode.pyc
iservices/rssdocument/browser/rssdocument.pt
iservices/rssdocument/browser/resources/jquery.zrssfeed.min.js
iservices/rssdocument/content/__init__.py
iservices/rssdocument/content/__init__.pyc
iservices/rssdocument/content/rssdocument.py
iservices/rssdocument/content/rssdocument.pyc
iservices/rssdocument/profiles/default/browserlayer.xml
iservices/rssdocument/profiles/default/factorytool.xml
iservices/rssdocument/profiles/default/metadata.xml
iservices/rssdocument/profiles/default/rolemap.xml
iservices/rssdocument/profiles/default/types.xml
iservices/rssdocument/profiles/default/types/RSSDocument.xml
iservices/rssdocument/tests/__init__.py
iservices/rssdocument/tests/base.py
iservices/rssdocument/tests/functional.txt
iservices/rssdocument/tests/test_functional_doctest.py
iservices/rssdocument/tests/test_setup.py