Metadata-Version: 1.0
Name: iservices.rssdocument
Version: 0.5.0
Summary: A dynamic RSS content-type for plone
Home-page: http://svn.plone.org/svn/collective/iservices.rssdocument
Author: Noe Nieto
Author-email: desarrollo@iservices.com.mx
License: LGPL
Keywords: Plone,RSS,jQuery
Platform: UNKNOWN
Classifier: Framework :: Plone
Classifier: Programming Language :: Python
Classifier: Programming Language :: JavaScript
Classifier: Topic :: Text Processing :: Markup :: HTML
Classifier: Development Status :: 4 - Beta
Classifier: Framework :: Plone
